swordfish/__init__.py
swordfish/_config.py
swordfish/_connection.py
swordfish/_core.py
swordfish/_engine.py
swordfish/_enums.py
swordfish/_function_bindings.py
swordfish/_function_tools.py
swordfish/_helper.py
swordfish/_runtime.py
swordfish/_sqlbuilder.py
swordfish/_streaming.py
swordfish/_swordfishcpp.cpython-39-x86_64-linux-gnu.so
swordfish/_swordfishcpp.pyi
swordfish/_translator.py
swordfish/connection.py
swordfish/data.py
swordfish/engine.py
swordfish/enums.py
swordfish/function.py
swordfish/infos.py
swordfish/io.py
swordfish/module.py
swordfish/streaming.py
swordfish/tools.py
swordfish/types.py
swordfish/asset/dolphindb.dos
swordfish/plugins/__init__.py
swordfish/plugins/matching_engine_simulator.py
swordfish/plugins/backtest/__init__.py
swordfish/plugins/backtest/backtest.py
swordfish/plugins/backtest/translator.py
pyswordfish-3.0.4.1.dist-info/METADATA
pyswordfish-3.0.4.1.dist-info/WHEEL
pyswordfish-3.0.4.1.dist-info/top_level.txt
pyswordfish-3.0.4.1.dist-info/RECORD
pyswordfish.libs/libclucene-core-ecf77c55.so
pyswordfish.libs/libclucene-shared-fb24082b.so
pyswordfish.libs/libgfortran-6f8c99d4.so.5
pyswordfish.libs/libopenblas-318ba409.so.0
pyswordfish.libs/libclucene-contribs-lib-dec0298b.so
pyswordfish.libs/libuuid-f64cda11.so.1
pyswordfish.libs/libSwordfish-c03e2d55.so
pyswordfish.libs/libquadmath-96973f99.so.0
