Metadata-Version: 2.1
Name: pyswordfish
Version: 3.0.4.1
Summary: High-performance embedded computing engine and database developed by DolphinDB.
Home-page: https://docs.dolphindb.com/en/swordfish/what_is_swordfish.html
Author: DolphinDB, Inc.
Author-email: support@dolphindb.com
License: DolphinDB
Platform: Linux
Platform: Windows
Classifier: Programming Language :: Python
Classifier: Programming Language :: Python :: 3
Classifier: Programming Language :: Python :: 3.8
Classifier: Programming Language :: Python :: 3.9
Classifier: Programming Language :: Python :: 3.10
Classifier: Programming Language :: Python :: 3.11
Classifier: Programming Language :: Python :: 3.12
Classifier: Programming Language :: Python :: Implementation :: CPython
Classifier: Operating System :: POSIX :: Linux
Classifier: Operating System :: Microsoft :: Windows
Requires-Python: >=3.8
Requires-Dist: numpy>=1.18.0
Requires-Dist: pandas!=1.3.0,>=1.0.0
Requires-Dist: future
Requires-Dist: packaging
Requires-Dist: toml
